Metadata-Version: 1.0
Name: ztf-auth
Version: 0.0.3
Summary: simple script to obtain authentication parameters from a file
Home-page: UNKNOWN
Author: UNKNOWN
Author-email: UNKNOWN
License: UNKNOWN
Platform: UNKNOWN
